{
  "shein.com": [
    {
      "code": "UAE",
      "description": "100% Verified SHEIN Coupons & Discount Codes UAE - 2026",
      "successRate": 0.2
    },
    {
      "code": "100",
      "description": "100% Verified SHEIN Coupons & Discount Codes UAE - 2026",
      "successRate": 0.2
    },
    {
      "code": "SHEIN",
      "description": "100% Verified SHEIN Coupons & Discount Codes UAE - 2026",
      "successRate": 0.2
    },
    {
      "code": "ALCP",
      "description": "100% Verified SHEIN Coupons & Discount Codes UAE - 2026",
      "successRate": 0.2
    },
    {
      "code": "400",
      "description": "100% Verified SHEIN Coupons & Discount Codes UAE - 2026",
      "successRate": 0.2
    },
    {
      "code": "MEAF25",
      "description": "100% Verified SHEIN Coupons & Discount Codes UAE - 2026",
      "successRate": 0.2
    },
    {
      "code": "102",
      "description": "100% Verified SHEIN Coupons & Discount Codes UAE - 2026",
      "successRate": 0.2
    },
    {
      "code": "509",
      "description": "100% Verified SHEIN Coupons & Discount Codes UAE - 2026",
      "successRate": 0.2
    }
  ],
  "adidas.com": [
    {
      "code": "UAE",
      "description": "Adidas Online Coupon Codes & Discounts 2026 | Up to 50% OFF",
      "successRate": 0.5
    },
    {
      "code": "RAN13",
      "description": "Adidas Online Coupon Codes & Discounts 2026 | Up to 50% OFF",
      "successRate": 0.5
    },
    {
      "code": "AED",
      "description": "Adidas Online Coupon Codes & Discounts 2026 | Up to 50% OFF",
      "successRate": 0.5
    },
    {
      "code": "392",
      "description": "Adidas Online Coupon Codes & Discounts 2026 | Up to 50% OFF",
      "successRate": 0.5
    },
    {
      "code": "400",
      "description": "Adidas Online Coupon Codes & Discounts 2026 | Up to 50% OFF",
      "successRate": 0.5
    },
    {
      "code": "194",
      "description": "Adidas Online Coupon Codes & Discounts 2026 | Up to 50% OFF",
      "successRate": 0.5
    },
    {
      "code": "103",
      "description": "Adidas Online Coupon Codes & Discounts 2026 | Up to 50% OFF",
      "successRate": 0.5
    },
    {
      "code": "250",
      "description": "Adidas Online Coupon Codes & Discounts 2026 | Up to 50% OFF",
      "successRate": 0.5
    }
  ],
  "storeus.com": [
    {
      "code": "UAE",
      "description": "Storeus coupon code 2026 | 15% off sitewide",
      "successRate": 0.2
    },
    {
      "code": "400",
      "description": "Storeus coupon code 2026 | 15% off sitewide",
      "successRate": 0.2
    },
    {
      "code": "R88",
      "description": "Storeus coupon code 2026 | 15% off sitewide",
      "successRate": 0.2
    },
    {
      "code": "ALCP15",
      "description": "Storeus coupon code 2026 | 15% off sitewide",
      "successRate": 0.2
    },
    {
      "code": "486",
      "description": "Storeus coupon code 2026 | 15% off sitewide",
      "successRate": 0.2
    },
    {
      "code": "100",
      "description": "Storeus coupon code 2026 | 15% off sitewide",
      "successRate": 0.2
    },
    {
      "code": "ALCPN",
      "description": "Storeus coupon code 2026 | 15% off sitewide",
      "successRate": 0.2
    },
    {
      "code": "SMS",
      "description": "Storeus coupon code 2026 | 15% off sitewide",
      "successRate": 0.2
    }
  ],
  "noon.com": [
    {
      "code": "UAE",
      "description": "Noon Discount Codes & Coupons 2026 | Up to 80% in UAE",
      "successRate": 0.8
    },
    {
      "code": "ALC54",
      "description": "Noon Discount Codes & Coupons 2026 | Up to 80% in UAE",
      "successRate": 0.8
    },
    {
      "code": "SAVE",
      "description": "Noon Discount Codes & Coupons 2026 | Up to 80% in UAE",
      "successRate": 0.8
    },
    {
      "code": "NOW",
      "description": "Noon Discount Codes & Coupons 2026 | Up to 80% in UAE",
      "successRate": 0.8
    },
    {
      "code": "400",
      "description": "Noon Discount Codes & Coupons 2026 | Up to 80% in UAE",
      "successRate": 0.8
    },
    {
      "code": "ALC59",
      "description": "Noon Discount Codes & Coupons 2026 | Up to 80% in UAE",
      "successRate": 0.8
    },
    {
      "code": "419",
      "description": "Noon Discount Codes & Coupons 2026 | Up to 80% in UAE",
      "successRate": 0.8
    },
    {
      "code": "AED",
      "description": "Noon Discount Codes & Coupons 2026 | Up to 80% in UAE",
      "successRate": 0.8
    }
  ],
  "trendyol.com": [
    {
      "code": "UAE",
      "description": "Trendyol Discount Code 2026 Latest Codes & Coupons Up to 90%",
      "successRate": 0.9
    },
    {
      "code": "RAGHDX",
      "description": "Trendyol Discount Code 2026 Latest Codes & Coupons Up to 90%",
      "successRate": 0.9
    },
    {
      "code": "400",
      "description": "Trendyol Discount Code 2026 Latest Codes & Coupons Up to 90%",
      "successRate": 0.9
    },
    {
      "code": "100",
      "description": "Trendyol Discount Code 2026 Latest Codes & Coupons Up to 90%",
      "successRate": 0.9
    },
    {
      "code": "126",
      "description": "Trendyol Discount Code 2026 Latest Codes & Coupons Up to 90%",
      "successRate": 0.9
    },
    {
      "code": "186",
      "description": "Trendyol Discount Code 2026 Latest Codes & Coupons Up to 90%",
      "successRate": 0.9
    },
    {
      "code": "MEGA",
      "description": "Trendyol Discount Code 2026 Latest Codes & Coupons Up to 90%",
      "successRate": 0.9
    },
    {
      "code": "112",
      "description": "Trendyol Discount Code 2026 Latest Codes & Coupons Up to 90%",
      "successRate": 0.9
    }
  ],
  "babystore.ae": [
    {
      "code": "UAE",
      "description": "BabyStore online | 10% BabyStore coupon codes UAE",
      "successRate": 0.2
    },
    {
      "code": "400",
      "description": "BabyStore online | 10% BabyStore coupon codes UAE",
      "successRate": 0.2
    },
    {
      "code": "507",
      "description": "BabyStore online | 10% BabyStore coupon codes UAE",
      "successRate": 0.2
    },
    {
      "code": "NEW10",
      "description": "BabyStore online | 10% BabyStore coupon codes UAE",
      "successRate": 0.2
    },
    {
      "code": "BS12",
      "description": "BabyStore online | 10% BabyStore coupon codes UAE",
      "successRate": 0.2
    },
    {
      "code": "101",
      "description": "BabyStore online | 10% BabyStore coupon codes UAE",
      "successRate": 0.2
    },
    {
      "code": "100",
      "description": "BabyStore online | 10% BabyStore coupon codes UAE",
      "successRate": 0.2
    },
    {
      "code": "SMS",
      "description": "BabyStore online | 10% BabyStore coupon codes UAE",
      "successRate": 0.2
    }
  ]
}